odoo/addons/account_reconcile_analytic_tag/README.rst
odoo/addons/account_reconcile_analytic_tag/__init__.py
odoo/addons/account_reconcile_analytic_tag/__manifest__.py
odoo/addons/account_reconcile_analytic_tag/i18n/account_reconcile_analytic_tag.pot
odoo/addons/account_reconcile_analytic_tag/i18n/es.po
odoo/addons/account_reconcile_analytic_tag/i18n/it.po
odoo/addons/account_reconcile_analytic_tag/i18n/lv.po
odoo/addons/account_reconcile_analytic_tag/models/__init__.py
odoo/addons/account_reconcile_analytic_tag/models/account_bank_statement_line.py
odoo/addons/account_reconcile_analytic_tag/models/account_reconcile_abstract.py
odoo/addons/account_reconcile_analytic_tag/models/account_reconcile_model.py
odoo/addons/account_reconcile_analytic_tag/readme/CONTRIBUTORS.md
odoo/addons/account_reconcile_analytic_tag/readme/DESCRIPTION.md
odoo/addons/account_reconcile_analytic_tag/static/description/icon.png
odoo/addons/account_reconcile_analytic_tag/static/description/index.html
odoo/addons/account_reconcile_analytic_tag/tests/__init__.py
odoo/addons/account_reconcile_analytic_tag/tests/test_account_reconcile_analytic_tag.py
odoo/addons/account_reconcile_analytic_tag/views/account_bank_statement_line_views.xml
odoo/addons/account_reconcile_analytic_tag/views/account_reconcile_model_views.xml
odoo_addon_account_reconcile_analytic_tag-18.0.1.0.1.dist-info/METADATA
odoo_addon_account_reconcile_analytic_tag-18.0.1.0.1.dist-info/WHEEL
odoo_addon_account_reconcile_analytic_tag-18.0.1.0.1.dist-info/top_level.txt
odoo_addon_account_reconcile_analytic_tag-18.0.1.0.1.dist-info/RECORD
